{"default": {"PITCH0": {"blue": {"hsv_max": [118.0, 155.0, 88.0], "hsv_min": [68.0, 98.0, 71.0], "rgb_max": [118.0, 155.0, 88.0], "blur": 0, "contrast": 0.0, "rgb_min": [68.0, 98.0, 71.0]}, "plate": {"hsv_max": [118.0, 155.0, 88.0], "hsv_min": [68.0, 98.0, 71.0], "rgb_max": [118.0, 155.0, 88.0], "blur": 0, "contrast": 0.0, "rgb_min": [68.0, 98.0, 71.0]}, "dot": {"hsv_max": [118.0, 155.0, 88.0], "hsv_min": [68.0, 98.0, 71.0], "rgb_max": [118.0, 155.0, 88.0], "blur": 0, "contrast": 0.0, "rgb_min": [68.0, 98.0, 71.0]}, "yellow": {"hsv_max": [118.0, 155.0, 88.0], "hsv_min": [68.0, 98.0, 71.0], "rgb_max": [118.0, 155.0, 88.0], "blur": 0, "contrast": 0.0, "rgb_min": [68.0, 98.0, 71.0]}, "red": {"hsv_max": [118.0, 155.0, 88.0], "hsv_min": [68.0, 98.0, 71.0], "rgb_max": [118.0, 155.0, 88.0], "blur": 0, "contrast": 0.0, "rgb_min": [68.0, 98.0, 71.0]}}, "PITCH1": {"blue": {"hsv_max": [118.0, 155.0, 88.0], "hsv_min": [68.0, 98.0, 71.0], "rgb_max": [118.0, 155.0, 88.0], "blur": 0, "contrast": 0.0, "rgb_min": [68.0, 98.0, 71.0]}, "plate": {"hsv_max": [118.0, 155.0, 88.0], "hsv_min": [68.0, 98.0, 71.0], "rgb_max": [118.0, 155.0, 88.0], "blur": 0, "contrast": 0.0, "rgb_min": [68.0, 98.0, 71.0]}, "yellow": {"hsv_max": [118.0, 155.0, 88.0], "hsv_min": [68.0, 98.0, 71.0], "rgb_max": [118.0, 155.0, 88.0], "blur": 0, "contrast": 0.0, "rgb_min": [68.0, 98.0, 71.0]}, "red": {"hsv_max": [118.0, 155.0, 88.0], "hsv_min": [68.0, 98.0, 71.0], "rgb_max": [118.0, 155.0, 88.0], "blur": 0, "contrast": 0.0, "rgb_min": [68.0, 98.0, 71.0]}, "dot": {"hsv_max": [118.0, 155.0, 88.0], "hsv_min": [68.0, 98.0, 71.0], "rgb_max": [118.0, 155.0, 88.0], "blur": 0, "contrast": 0.0, "rgb_min": [68.0, 98.0, 71.0]}}}, "rothesay": {"PITCH0": {"blue": {"hsv_max": [118.0, 155.0, 88.0], "hsv_min": [68.0, 98.0, 71.0], "rgb_max": [118.0, 155.0, 88.0], "blur": 0, "contrast": 0.0, "rgb_min": [68.0, 98.0, 71.0]}, "plate": {"hsv_max": [118.0, 155.0, 88.0], "hsv_min": [68.0, 98.0, 71.0], "rgb_max": [118.0, 155.0, 88.0], "blur": 0, "contrast": 0.0, "rgb_min": [68.0, 98.0, 71.0]}, "yellow": {"hsv_max": [118.0, 155.0, 88.0], "hsv_min": [68.0, 98.0, 71.0], "rgb_max": [118.0, 155.0, 88.0], "blur": 0, "contrast": 0.0, "rgb_min": [68.0, 98.0, 71.0]}, "red": {"hsv_max": [118.0, 155.0, 88.0], "hsv_min": [68.0, 98.0, 71.0], "rgb_max": [118.0, 155.0, 88.0], "blur": 0, "contrast": 0.0, "rgb_min": [68.0, 98.0, 71.0]}, "dot": {"hsv_max": [118.0, 155.0, 88.0], "hsv_min": [68.0, 98.0, 71.0], "rgb_max": [118.0, 155.0, 88.0], "blur": 0, "contrast": 0.0, "rgb_min": [68.0, 98.0, 71.0]}}, "PITCH1": {"blue": {"hsv_max": [118.0, 155.0, 88.0], "hsv_min": [68.0, 98.0, 71.0], "rgb_max": [118.0, 155.0, 88.0], "blur": 0, "contrast": 0.0, "rgb_min": [68.0, 98.0, 71.0]}, "plate": {"hsv_max": [118.0, 155.0, 88.0], "hsv_min": [68.0, 98.0, 71.0], "rgb_max": [118.0, 155.0, 88.0], "blur": 0, "contrast": 0.0, "rgb_min": [68.0, 98.0, 71.0]}, "yellow": {"hsv_max": [118.0, 155.0, 88.0], "hsv_min": [68.0, 98.0, 71.0], "rgb_max": [118.0, 155.0, 88.0], "blur": 0, "contrast": 0.0, "rgb_min": [68.0, 98.0, 71.0]}, "red": {"hsv_max": [118.0, 155.0, 88.0], "hsv_min": [68.0, 98.0, 71.0], "rgb_max": [118.0, 155.0, 88.0], "blur": 0, "contrast": 0.0, "rgb_min": [68.0, 98.0, 71.0]}, "dot": {"hsv_max": [118.0, 155.0, 88.0], "hsv_min": [68.0, 98.0, 71.0], "rgb_max": [118.0, 155.0, 88.0], "blur": 0, "contrast": 0.0, "rgb_min": [68.0, 98.0, 71.0]}}}, "dunoon": {"PITCH0": {"blue": {"hsv_max": [110.0, 164.0, 120.0], "hsv_min": [86.0, 113.0, 65.0], "rgb_max": [129.0, 90.0, 54.0], "blur": 0, "contrast": 0.0, "rgb_min": [80.0, 68.0, 33.0]}, "plate": {"hsv_max": [123.0, 204.0, 132.0], "hsv_min": [26.0, 87.0, 90.0], "rgb_max": [64.0, 122.0, 66.0], "blur": 8, "contrast": 0.0, "rgb_min": [32.0, 95.0, 21.0]}, "yellow": {"hsv_max": [19.0, 255.0, 244.0], "hsv_min": [2.0, 191.0, 129.0], "rgb_max": [56.0, 143.0, 218.0], "blur": 0, "contrast": 0.0, "rgb_min": [4.0, 82.0, 96.0]}, "red": {"hsv_max": [197.0, 255.0, 202.0], "hsv_min": [0.0, 163.0, 118.0], "rgb_max": [245.0, 72.0, 217.0], "blur": 0, "contrast": 12.0, "rgb_min": [30.0, 15.0, 97.0]}, "dot": {"hsv_max": [93.0, 145.0, 110.0], "hsv_min": [22.0, 72.0, 48.0], "rgb_max": [48.0, 73.0, 56.0], "blur": 0, "contrast": 0.0, "rgb_min": [15.0, 41.0, 6.0]}}, "PITCH1": {"blue": {"hsv_max": [118.0, 155.0, 88.0], "hsv_min": [68.0, 98.0, 71.0], "rgb_max": [118.0, 155.0, 88.0], "blur": 0, "contrast": 0.0, "rgb_min": [68.0, 98.0, 71.0]}, "plate": {"hsv_max": [118.0, 155.0, 88.0], "hsv_min": [68.0, 98.0, 71.0], "rgb_max": [118.0, 155.0, 88.0], "blur": 0, "contrast": 0.0, "rgb_min": [68.0, 98.0, 71.0]}, "yellow": {"hsv_max": [118.0, 155.0, 88.0], "hsv_min": [68.0, 98.0, 71.0], "rgb_max": [118.0, 155.0, 88.0], "blur": 0, "contrast": 0.0, "rgb_min": [68.0, 98.0, 71.0]}, "red": {"hsv_max": [118.0, 155.0, 88.0], "hsv_min": [68.0, 98.0, 71.0], "rgb_max": [118.0, 155.0, 88.0], "blur": 0, "contrast": 0.0, "rgb_min": [68.0, 98.0, 71.0]}, "dot": {"hsv_max": [118.0, 155.0, 88.0], "hsv_min": [68.0, 98.0, 71.0], "rgb_max": [118.0, 155.0, 88.0], "blur": 0, "contrast": 0.0, "rgb_min": [68.0, 98.0, 71.0]}}}}